LICENCE
README.md
requirements.txt
setup.py
psypwdm/__init__.py
psypwdm/_connect.py
psypwdm/_create.py
psypwdm/_del.py
psypwdm/_insert.py
psypwdm/_out.py
psypwdm/_retrieve.py
psypwdm/config.ini
psypwdm.egg-info/PKG-INFO
psypwdm.egg-info/SOURCES.txt
psypwdm.egg-info/dependency_links.txt
psypwdm.egg-info/top_level.txt