Metadata-Version: 2.1
Name: psypwdm
Version: 1.0.1
Summary: An open source, local password manager written with python for postgres
Home-page: https://github.com/KshkB/local-password-manager
Author: Kowshik Bettadapura
Author-email: k.bettad@gmail.com
License: MIT
License-File: LICENCE
